{
  "_obj_class": "Page",
  "title": [
    "string",
    "Create ticket"
  ],
  "data": [
    "datalocator",
    {
      "class": "Ticket"
    }
  ],
  "body": [
    "widgetlist",
    [
      "25921a17",
      "f764dbd5"
    ]
  ],
  "robots_index": [
    "boolean",
    true
  ],
  "layout_main_background_color": [
    "string",
    "transparent"
  ],
  "_conflicts": null,
  "_content_id": "f909e9691db27360",
  "_created_at": "20240109075855",
  "_data_param": null,
  "_editing_asset": false,
  "_first_published_at": "20240112090022",
  "_id": "f909e9691db27360",
  "_language": "en",
  "_last_changed": "20250805132940",
  "_modification": null,
  "_path": "/33cbdf671c7b83b1/edd1e72884bf7d89/125f0003cf11c725/f909e9691db27360",
  "_permalink": null,
  "_published_at": "20250806071623",
  "_restriction": [
    "_auth"
  ],
  "_site_id": "56a14d0750cc844e",
  "_version": "202508060716230000000000000000297565bdf5c97a35",
  "_widget_pool": {
    "ca6026fe": {
      "_obj_class": "DataFormContainerWidget",
      "content": [
        "widgetlist",
        [
          "c1c694c9",
          "fcd15dfa",
          "68c55e2a",
          "c977b809",
          "31558d9d"
        ]
      ],
      "redirect_after_submit": [
        "boolean",
        true
      ]
    },
    "c1c694c9": {
      "_obj_class": "DataFormInputFieldWidget",
      "label": [
        "string",
        "Title"
      ],
      "type": [
        "string",
        "single_line"
      ],
      "required": [
        "boolean",
        true
      ],
      "data": [
        "datalocator",
        {
          "class": "Ticket",
          "field": "title",
          "via_ref": "multi"
        }
      ]
    },
    "31558d9d": {
      "_obj_class": "DataFormSubmitButtonWidget",
      "submit_title": [
        "string",
        "Create"
      ],
      "reset_title": [
        "string",
        "cancel"
      ],
      "size": [
        "string",
        "medium"
      ],
      "alignment": [
        "string",
        "left"
      ]
    },
    "68c55e2a": {
      "_obj_class": "DataFormOptionsWidget",
      "label": [
        "string",
        "Type"
      ],
      "options": [
        "stringlist",
        [
          "Question",
          "Fault",
          "Claim"
        ]
      ],
      "required": [
        "boolean",
        true
      ],
      "default_value": [
        "string",
        "PSA_SVC_CAL"
      ],
      "data": [
        "datalocator",
        {
          "class": "Ticket",
          "field": "type",
          "via_ref": "multi"
        }
      ]
    },
    "fcd15dfa": {
      "_obj_class": "DataFormInputFieldWidget",
      "label": [
        "string",
        "Description"
      ],
      "type": [
        "string",
        "multi_line"
      ],
      "required": [
        "boolean",
        true
      ],
      "data": [
        "datalocator",
        {
          "class": "Ticket",
          "field": "description",
          "via_ref": "multi"
        }
      ]
    },
    "f764dbd5": {
      "_obj_class": "CardWidget",
      "background_color": [
        "string",
        "light-grey"
      ],
      "padding": [
        "string",
        "p-4"
      ],
      "margin": [
        "string",
        "mb-4"
      ],
      "card_body": [
        "widgetlist",
        [
          "ca6026fe"
        ]
      ]
    },
    "25921a17": {
      "_obj_class": "HeadlineWidget",
      "alignment": [
        "string",
        "left"
      ],
      "headline": [
        "string",
        "Create ticket"
      ],
      "style": [
        "string",
        "h2"
      ],
      "margin": [
        "string",
        "mb-2"
      ]
    },
    "c977b809": {
      "_obj_class": "DataFormUploadWidget",
      "label": [
        "string",
        "Files"
      ],
      "multiple": [
        "boolean",
        true
      ],
      "data": [
        "datalocator",
        {
          "class": "Ticket",
          "field": "attachments",
          "via_ref": "multi"
        }
      ]
    }
  },
  "_created_by": "scrivito:65a0e747eaf64fa6a193cebce8470e71",
  "_first_published_by": "scrivito:65a0e747eaf64fa6a193cebce8470e71",
  "_last_changed_by": "scrivito:65a0e747eaf64fa6a193cebce8470e71",
  "_published_by": "scrivito:65a0e747eaf64fa6a193cebce8470e71"
}